jsonobj.py
jsonobj-0.1.0.dist-info/LICENSE
jsonobj-0.1.0.dist-info/METADATA
jsonobj-0.1.0.dist-info/WHEEL
jsonobj-0.1.0.dist-info/top_level.txt
jsonobj-0.1.0.dist-info/RECORD
